aquachain_tk-0.0.4.data/data/aquachaintk/aquachain.png
aquachain_tk-0.0.4.data/scripts/aquachain-tk
aquachain_tk-0.0.4.dist-info/METADATA
aquachain_tk-0.0.4.dist-info/RECORD
aquachain_tk-0.0.4.dist-info/WHEEL
aquachain_tk-0.0.4.dist-info/top_level.txt
aquachaintk/__init__.py
aquachaintk/aquachain.png
aquachaintk/blockcache.py
aquachaintk/filterlooper.py
aquachaintk/scenes.py
aquachaintk/testapp.py
aquachaintk/themed.py
aquachaintk/toolbar.py
aquachaintk/vsframe.py
