Metadata-Version: 2.1
Name: aquachain-tk
Version: 0.0.4
Summary: Aquachain TK wallet for Python 3.6.5
Home-page: https://github.com/aquachain/aquachain-tk
Author: Aquachain Authors
Author-email: aquachain@riseup.net
License: GPL
Platform: UNKNOWN
Classifier: Development Status :: 2 - Pre-Alpha
Classifier: License :: Free for non-commercial use
Classifier: License :: OSI Approved :: GNU General Public License (GPL)
Requires-Dist: aquachain.py
